{
  "id": "4567541fb4f86760",
  "title": "More than 31 , 000 nurses , health care workers strike at Kaiser Permanente , arguing for safe staffing levels , fair wages",
  "description": "20260126T234500Z",
  "content": "",
  "source": "kbtt.fm",
  "source_url": "https://www.kbtt.fm/syndicated-article/?id=1656462",
  "published_at": "20260126T234500Z",
  "fetched_at": "2026-01-27T00:25:22.667063+00:00",
  "category": "labor_employment",
  "subcategory": null,
  "keywords": [
    "ai",
    "strike",
    "wage"
  ],
  "location": "United States",
  "raw_data": {
    "url": "https://www.kbtt.fm/syndicated-article/?id=1656462",
    "url_mobile": "",
    "title": "More than 31 , 000 nurses , health care workers strike at Kaiser Permanente , arguing for safe staffing levels , fair wages",
    "seendate": "20260126T234500Z",
    "socialimage": "https://www.alphamediahub.com/wp-content/uploads/2026/01/G_kaiser_012626.jpg?icb=1769470353",
    "domain": "kbtt.fm",
    "language": "English",
    "sourcecountry": "United States"
  }
}