{
  "id": "7c58a0ff2c27df4d",
  "title": "Greve dos petroleiros : Petrobras garante que n\u00e3o vai faltar combust\u00edvel | Tribuna Online",
  "description": "20251215T203000Z",
  "content": "",
  "source": "tribunaonline.com.br",
  "source_url": "https://tribunaonline.com.br/economia/greve-dos-petroleiros-petrobras-garante-que-nao-vai-faltar-combustivel-285051",
  "published_at": "20251215T203000Z",
  "fetched_at": "2025-12-16T00:23:22.810654+00:00",
  "category": "labor_employment",
  "subcategory": null,
  "keywords": [
    "ai"
  ],
  "location": "Brazil",
  "raw_data": {
    "url": "https://tribunaonline.com.br/economia/greve-dos-petroleiros-petrobras-garante-que-nao-vai-faltar-combustivel-285051",
    "url_mobile": "https://tribunaonline.com.br/economia/greve-dos-petroleiros-petrobras-garante-que-nao-vai-faltar-combustivel-285051?_=amp",
    "title": "Greve dos petroleiros : Petrobras garante que n\u00e3o vai faltar combust\u00edvel | Tribuna Online",
    "seendate": "20251215T203000Z",
    "socialimage": "https://cdn2.tribunaonline.com.br/img/Artigo-Destaque/280000/Greve-dos-petroleiros-Petrobras-garante-que-nao-va0028505100202512151532.jpg?xid=1304684",
    "domain": "tribunaonline.com.br",
    "language": "Portuguese",
    "sourcecountry": "Brazil"
  }
}