{
  "id": "495bced348db135c",
  "title": "M\u00fcnchner Sicherheitskonferenz : Es war einmal der Westen",
  "description": "20260215T224500Z",
  "content": "",
  "source": "taz.de",
  "source_url": "https://taz.de/Muenchner-Sicherheitskonferenz/!6154819/",
  "published_at": "20260215T224500Z",
  "fetched_at": "2026-02-16T00:29:41.976443+00:00",
  "category": "geopolitics_security",
  "subcategory": null,
  "keywords": [],
  "location": "Germany",
  "raw_data": {
    "url": "https://taz.de/Muenchner-Sicherheitskonferenz/!6154819/",
    "url_mobile": "",
    "title": "M\u00fcnchner Sicherheitskonferenz : Es war einmal der Westen",
    "seendate": "20260215T224500Z",
    "socialimage": "https://taz.de/picture/8253550/1200/40418252.jpeg",
    "domain": "taz.de",
    "language": "German",
    "sourcecountry": "Germany"
  }
}