{
  "id": "23adc35a314e364c",
  "title": "Elon Musk veut vider les caisses dOpenAI et Microsoft : il r\u00e9clame 134 milliards de dollars",
  "description": "20260119T164500Z",
  "content": "",
  "source": "numerama.com",
  "source_url": "https://www.numerama.com/tech/2162719-elon-musk-veut-vider-les-caisses-dopenai-et-microsoft-il-reclame-134-milliards-de-dollars.html",
  "published_at": "20260119T164500Z",
  "fetched_at": "2026-01-20T00:23:08.181708+00:00",
  "category": "space_frontier",
  "subcategory": null,
  "keywords": [
    "ai"
  ],
  "location": "France",
  "raw_data": {
    "url": "https://www.numerama.com/tech/2162719-elon-musk-veut-vider-les-caisses-dopenai-et-microsoft-il-reclame-134-milliards-de-dollars.html",
    "url_mobile": "",
    "title": "Elon Musk veut vider les caisses dOpenAI et Microsoft : il r\u00e9clame 134 milliards de dollars",
    "seendate": "20260119T164500Z",
    "socialimage": "https://c0.lestechnophiles.com/www.numerama.com/wp-content/uploads/2026/01/elon-musk-sam-altman.jpg",
    "domain": "numerama.com",
    "language": "French",
    "sourcecountry": "France"
  }
}