{
  "id": "ec4f847941214725",
  "title": "2 AI Stocks Predicted to Surpass Nvidia Value by 2026 End",
  "description": "20251223T154500Z",
  "content": "",
  "source": "el-balad.com",
  "source_url": "https://www.el-balad.com/6801956",
  "published_at": "20251223T154500Z",
  "fetched_at": "2025-12-24T00:22:47.431682+00:00",
  "category": "robotics_automation",
  "subcategory": null,
  "keywords": [
    "ai"
  ],
  "location": "Egypt",
  "raw_data": {
    "url": "https://www.el-balad.com/6801956",
    "url_mobile": "",
    "title": "2 AI Stocks Predicted to Surpass Nvidia Value by 2026 End",
    "seendate": "20251223T154500Z",
    "socialimage": "https://www.el-balad.com/uploads/images/202512/image_1200x675_694aac1c013db.webp",
    "domain": "el-balad.com",
    "language": "English",
    "sourcecountry": "Egypt"
  }
}