{
  "id": "bcceb3babfc3a240",
  "title": "High Country News | Classifieds | Employment & Education | Climate and Energy Program Associate",
  "description": "20260214T223000Z",
  "content": "",
  "source": "classifieds.hcn.org",
  "source_url": "https://classifieds.hcn.org/denver/employment-education/climate-and-energy-program-associate/86790c3015634325b2177bddc9ff",
  "published_at": "20260214T223000Z",
  "fetched_at": "2026-02-15T00:30:56.287245+00:00",
  "category": "climate_environment",
  "subcategory": null,
  "keywords": [
    "climate",
    "energy"
  ],
  "location": "United States",
  "raw_data": {
    "url": "https://classifieds.hcn.org/denver/employment-education/climate-and-energy-program-associate/86790c3015634325b2177bddc9ff",
    "url_mobile": "",
    "title": "High Country News | Classifieds | Employment & Education | Climate and Energy Program Associate",
    "seendate": "20260214T223000Z",
    "socialimage": "",
    "domain": "classifieds.hcn.org",
    "language": "English",
    "sourcecountry": "United States"
  }
}