{
  "id": "021ab8b3d0c74737",
  "title": "Bondi attack victims honored ; Australian prime minister booed",
  "description": "20251221T233000Z",
  "content": "",
  "source": "staradvertiser.com",
  "source_url": "https://www.staradvertiser.com/2025/12/21/breaking-news/bondi-attack-victims-honored-australian-prime-minister-booed/",
  "published_at": "20251221T233000Z",
  "fetched_at": "2025-12-22T00:24:16.044990+00:00",
  "category": "politics_governance",
  "subcategory": null,
  "keywords": [],
  "location": "United States",
  "raw_data": {
    "url": "https://www.staradvertiser.com/2025/12/21/breaking-news/bondi-attack-victims-honored-australian-prime-minister-booed/",
    "url_mobile": "",
    "title": "Bondi attack victims honored ; Australian prime minister booed",
    "seendate": "20251221T233000Z",
    "socialimage": "https://www.staradvertiser.com/wp-content/uploads/2023/02/Star-Advertiser-thumbnail-image.jpg",
    "domain": "staradvertiser.com",
    "language": "English",
    "sourcecountry": "United States"
  }
}