{
  "id": "57d63e112b530da7",
  "title": "La izquierda aprovecha el desastre del PSOE con un resultado hist\u00f3rico que debilita a Yolanda D\u00edaz",
  "description": "20251221T224500Z",
  "content": "",
  "source": "elconfidencial.com",
  "source_url": "https://www.elconfidencial.com/espana/2025-12-21/la-izquierda-aprovecha-el-desastre-del-psoe-mejor-resultado-historico-y-dardo-a-yolanda-diaz_4271132/",
  "published_at": "20251221T224500Z",
  "fetched_at": "2025-12-22T00:24:16.044990+00:00",
  "category": "politics_governance",
  "subcategory": null,
  "keywords": [],
  "location": "Spain",
  "raw_data": {
    "url": "https://www.elconfidencial.com/espana/2025-12-21/la-izquierda-aprovecha-el-desastre-del-psoe-mejor-resultado-historico-y-dardo-a-yolanda-diaz_4271132/",
    "url_mobile": "",
    "title": "La izquierda aprovecha el desastre del PSOE con un resultado hist\u00f3rico que debilita a Yolanda D\u00edaz",
    "seendate": "20251221T224500Z",
    "socialimage": "https://images.ecestaticos.com/jGClhy-EekesVRta4xPSjrWIRHg=/0x0:2272x1515/600x315/filters:fill(white):format(jpg):quality(99):watermark(f.elconfidencial.com/file/bae/eea/fde/baeeeafde1b3229287b0c008f7602058.png,0,275,1)/f.elconfidencial.com/original/144/b3d/9a7/144b3d9a7d5e672b7ace420fa0ffaed2.jpg",
    "domain": "elconfidencial.com",
    "language": "Spanish",
    "sourcecountry": "Spain"
  }
}