{
  "id": "0e4e5e4e46078bc4",
  "title": "Attaque DDoS record de 31 , 4 Tbps : comment des botnets transforme ... ",
  "description": "20260203T160000Z",
  "content": "",
  "source": "zdnet.fr",
  "source_url": "https://www.zdnet.fr/actualites/attaque-ddos-record-de-314-tbps-comment-des-botnets-transforment-vos-appareils-connectes-en-armes-numeriques-489346.htm",
  "published_at": "20260203T160000Z",
  "fetched_at": "2026-02-04T00:26:40.270602+00:00",
  "category": "geopolitics_security",
  "subcategory": null,
  "keywords": [],
  "location": "France",
  "raw_data": {
    "url": "https://www.zdnet.fr/actualites/attaque-ddos-record-de-314-tbps-comment-des-botnets-transforment-vos-appareils-connectes-en-armes-numeriques-489346.htm",
    "url_mobile": "",
    "title": "Attaque DDoS record de 31 , 4 Tbps : comment des botnets transforme ... ",
    "seendate": "20260203T160000Z",
    "socialimage": "https://www.zdnet.fr/wp-content/uploads/zdnet/2026/02/gettyimages-1393843200-1.webp",
    "domain": "zdnet.fr",
    "language": "French",
    "sourcecountry": "France"
  }
}