{
  "id": "dca85b0a3b0ec812",
  "title": "US clears Samsung , SK Hynix tool shipments to China",
  "description": "20251230T070000Z",
  "content": "",
  "source": "news.az",
  "source_url": "https://news.az/news/us-clears-samsung-sk-hynix-tool-shipments-to-china",
  "published_at": "20251230T070000Z",
  "fetched_at": "2025-12-31T00:23:34.453563+00:00",
  "category": "semiconductors_compute",
  "subcategory": null,
  "keywords": [
    "china"
  ],
  "location": "Azerbaijan",
  "raw_data": {
    "url": "https://news.az/news/us-clears-samsung-sk-hynix-tool-shipments-to-china",
    "url_mobile": "",
    "title": "US clears Samsung , SK Hynix tool shipments to China",
    "seendate": "20251230T070000Z",
    "socialimage": "https://news.az/photos/2025/12/1767074757.webp",
    "domain": "news.az",
    "language": "English",
    "sourcecountry": "Azerbaijan"
  }
}