{
  "id": "38cf2df3227043e8",
  "title": "KALW Almanac - Wednesday February 18 , 2026",
  "description": "20260218T161500Z",
  "content": "",
  "source": "kalw.org",
  "source_url": "https://www.kalw.org/show/the-kalw-morning-almanac/2026-02-18/kalw-almanac-wednesday-february-18-2026",
  "published_at": "20260218T161500Z",
  "fetched_at": "2026-02-19T00:30:34.211663+00:00",
  "category": "politics_governance",
  "subcategory": null,
  "keywords": [],
  "location": "United States",
  "raw_data": {
    "url": "https://www.kalw.org/show/the-kalw-morning-almanac/2026-02-18/kalw-almanac-wednesday-february-18-2026",
    "url_mobile": "",
    "title": "KALW Almanac - Wednesday February 18 , 2026",
    "seendate": "20260218T161500Z",
    "socialimage": "http://npr-brightspot.s3.amazonaws.com/5f/37/2aab56094641a8b3b7b1841bf6dc/19540320858-ff08358b17-c.jpg",
    "domain": "kalw.org",
    "language": "English",
    "sourcecountry": "United States"
  }
}