{
  "id": "ca14b51ee1bc5de6",
  "title": "Putin Heads to New Delhi",
  "description": "The visit comes at a somewhat precarious moment for India-Russia relations.",
  "content": "Welcome to\u00a0Foreign Policys South Asia Brief.\r\nThe highlights this week: Russian President Vladimir Putin visits India for the first time since his full-scale invasion of Ukraine, Sri Lanka grapples w\u2026 [+8900 chars]",
  "source": "Foreign Policy",
  "source_url": "http://foreignpolicy.com/2025/12/03/putin-new-delhi-trip-modi-india-russia-energy/",
  "published_at": "2025-12-03T21:31:21Z",
  "fetched_at": "2025-12-06T18:33:06.472112+00:00",
  "category": "geopolitics_security",
  "subcategory": null,
  "keywords": [
    "russia",
    "search:mental health crisis"
  ],
  "location": null,
  "raw_data": {
    "source": {
      "id": null,
      "name": "Foreign Policy"
    },
    "author": "Michael Kugelman",
    "title": "Putin Heads to New Delhi",
    "description": "The visit comes at a somewhat precarious moment for India-Russia relations.",
    "url": "http://foreignpolicy.com/2025/12/03/putin-new-delhi-trip-modi-india-russia-energy/",
    "urlToImage": "https://foreignpolicy.com/wp-content/uploads/2025/12/putin-modi-meeting-GettyImages-2232549333.jpg?w=1000",
    "publishedAt": "2025-12-03T21:31:21Z",
    "content": "Welcome to\u00a0Foreign Policys South Asia Brief.\r\nThe highlights this week: Russian President Vladimir Putin visits India for the first time since his full-scale invasion of Ukraine, Sri Lanka grapples w\u2026 [+8900 chars]"
  }
}