{
  "id": "f224bea394ce5ad8",
  "title": "\u0130srail , L\u00fcbnan  \u0131n Do\u011fusundaki Hava Sald\u0131r\u0131s\u0131nda \u0130ranl\u0131 Komutan\u0131 Vurdu",
  "description": "20251225T163000Z",
  "content": "",
  "source": "mersinhaber.com",
  "source_url": "https://www.mersinhaber.com/haber-israil-lubnanin-dogusundaki-hava-saldirisinda-iranli-komutani-vurdu/502502",
  "published_at": "20251225T163000Z",
  "fetched_at": "2025-12-26T00:22:56.644001+00:00",
  "category": "geopolitics_security",
  "subcategory": null,
  "keywords": [
    "ai"
  ],
  "location": "Turkey",
  "raw_data": {
    "url": "https://www.mersinhaber.com/haber-israil-lubnanin-dogusundaki-hava-saldirisinda-iranli-komutani-vurdu/502502",
    "url_mobile": "https://www.mersinhaber.com/amp/haber/502502",
    "title": "\u0130srail , L\u00fcbnan  \u0131n Do\u011fusundaki Hava Sald\u0131r\u0131s\u0131nda \u0130ranl\u0131 Komutan\u0131 Vurdu",
    "seendate": "20251225T163000Z",
    "socialimage": "https://www.mersinhaber.com/cropp/1200x675/Depo/haber/502502/org/502502.webp",
    "domain": "mersinhaber.com",
    "language": "Turkish",
    "sourcecountry": "Turkey"
  }
}