{
  "id": "5ee8c02cc683bfd1",
  "title": "Trump Media takes on fusion in $6B merger",
  "description": "20251218T213000Z",
  "content": "",
  "source": "eenews.net",
  "source_url": "https://www.eenews.net/articles/trump-media-takes-on-fusion-in-6b-merger/",
  "published_at": "20251218T213000Z",
  "fetched_at": "2025-12-19T00:23:08.544189+00:00",
  "category": "energy_resources",
  "subcategory": null,
  "keywords": [
    "fusion"
  ],
  "location": "United States",
  "raw_data": {
    "url": "https://www.eenews.net/articles/trump-media-takes-on-fusion-in-6b-merger/",
    "url_mobile": "",
    "title": "Trump Media takes on fusion in $6B merger",
    "seendate": "20251218T213000Z",
    "socialimage": "https://static.politico.com/73/82/5a8298fd495da4ace738b306e14f/trump-media-fusion-energy-28333.jpg",
    "domain": "eenews.net",
    "language": "English",
    "sourcecountry": "United States"
  }
}