{
  "id": "d8b4a03e201219ca",
  "title": "Porteremo lEuropa su Marte - ItaliaOggi . it",
  "description": "20260219T211500Z",
  "content": "",
  "source": "italiaoggi.it",
  "source_url": "https://www.italiaoggi.it/economia-e-politica/economia-e-finanza/porteremo-leuropa-su-marte-n9utk5le",
  "published_at": "20260219T211500Z",
  "fetched_at": "2026-02-20T00:27:32.210173+00:00",
  "category": "robotics_automation",
  "subcategory": null,
  "keywords": [],
  "location": "Italy",
  "raw_data": {
    "url": "https://www.italiaoggi.it/economia-e-politica/economia-e-finanza/porteremo-leuropa-su-marte-n9utk5le",
    "url_mobile": "",
    "title": "Porteremo lEuropa su Marte - ItaliaOggi . it",
    "seendate": "20260219T211500Z",
    "socialimage": "https://images.class.atexcloud.io/view/acePublic/alias/contentid/1107f43c-7652-4b58-a98f-a50b259faec1/0/valentinj-jpg.webp",
    "domain": "italiaoggi.it",
    "language": "Italian",
    "sourcecountry": "Italy"
  }
}