{
  "id": "51aa9c2a25c72066",
  "title": "\u5317\u6377\u6050\u653b\u91c04\u6b7b9\u50b7 \uff01 \u5f35\u6587\u7a7a\u8ecd\u9000\u4f0d\u80cc\u666f\u66dd \u300c \u907a\u843d\u7b46\u8a18\u672c \u300d \u6210\u7834\u6848\u95dc\u9375 | \u793e\u6703 | \u4e09\u7acb\u65b0\u805e\u7db2 SETN . COM",
  "description": "20251219T233000Z",
  "content": "",
  "source": "setn.com",
  "source_url": "https://www.setn.com/News.aspx?NewsID=1768265",
  "published_at": "20251219T233000Z",
  "fetched_at": "2025-12-20T00:22:03.659749+00:00",
  "category": "geopolitics_security",
  "subcategory": null,
  "keywords": [],
  "location": "Taiwan",
  "raw_data": {
    "url": "https://www.setn.com/News.aspx?NewsID=1768265",
    "url_mobile": "https://www.setn.com/m/ampnews.aspx?NewsID=1768265",
    "title": "\u5317\u6377\u6050\u653b\u91c04\u6b7b9\u50b7 \uff01 \u5f35\u6587\u7a7a\u8ecd\u9000\u4f0d\u80cc\u666f\u66dd \u300c \u907a\u843d\u7b46\u8a18\u672c \u300d \u6210\u7834\u6848\u95dc\u9375 | \u793e\u6703 | \u4e09\u7acb\u65b0\u805e\u7db2 SETN . COM",
    "seendate": "20251219T233000Z",
    "socialimage": "https://attach.setn.com/newsimages/2025/12/19/5389919-PH.jpg",
    "domain": "setn.com",
    "language": "Chinese",
    "sourcecountry": "Taiwan"
  }
}