{
  "id": "e253abe36ca04e32",
  "title": "Rus hackerlar Bel\u00e7ikaya sald\u0131rd\u0131",
  "description": "20251219T213000Z",
  "content": "",
  "source": "odatv.com",
  "source_url": "https://www.odatv.com/guncel/rus-hackerlar-belcikaya-saldirdi-120127978",
  "published_at": "20251219T213000Z",
  "fetched_at": "2025-12-20T00:22:03.659749+00:00",
  "category": "geopolitics_security",
  "subcategory": null,
  "keywords": [],
  "location": "Turkey",
  "raw_data": {
    "url": "https://www.odatv.com/guncel/rus-hackerlar-belcikaya-saldirdi-120127978",
    "url_mobile": "https://www.odatv.com/amp/guncel/rus-hackerlar-belcikaya-saldirdi-120127978",
    "title": "Rus hackerlar Bel\u00e7ikaya sald\u0131rd\u0131",
    "seendate": "20251219T213000Z",
    "socialimage": "https://img.odatv.com/rcman/Cw1280h720q95gc/storage/files/images/2025/12/19/rus-hackerlar-belcikaya-saldirdi-sdiu.jpg",
    "domain": "odatv.com",
    "language": "Turkish",
    "sourcecountry": "Turkey"
  }
}