{
  "id": "154e7941e25bfd7a",
  "title": "Everything you need to know as huge Chinese car firm comes to Liverpool",
  "description": "20260131T144500Z",
  "content": "",
  "source": "liverpoolecho.co.uk",
  "source_url": "https://www.liverpoolecho.co.uk/news/liverpool-news/everything-you-need-know-huge-33332464",
  "published_at": "20260131T144500Z",
  "fetched_at": "2026-02-01T00:32:37.375926+00:00",
  "category": "robotics_automation",
  "subcategory": null,
  "keywords": [],
  "location": "United Kingdom",
  "raw_data": {
    "url": "https://www.liverpoolecho.co.uk/news/liverpool-news/everything-you-need-know-huge-33332464",
    "url_mobile": "",
    "title": "Everything you need to know as huge Chinese car firm comes to Liverpool",
    "seendate": "20260131T144500Z",
    "socialimage": "https://i2-prod.liverpoolecho.co.uk/article33326020.ece/ALTERNATES/s1200/0_Spekecars1jpgLiv.jpg",
    "domain": "liverpoolecho.co.uk",
    "language": "English",
    "sourcecountry": "United Kingdom"
  }
}