{
  "id": "fc9a02659da9e3de",
  "title": "\ube45\ud14c\ud06c AI\uce69 \ud328\uad8c \uc804\uc7c1 \u2026 \uc0bc\uc131 \u00b7 SK\ub3c4  \uba54\ubaa8\ub9ac \uc591\uac15  \uad73\ud78c\ub2e4",
  "description": "20251214T061500Z",
  "content": "",
  "source": "edaily.co.kr",
  "source_url": "https://www.edaily.co.kr/News/Read?newsId=01646566642398520&mediaCodeNo=257",
  "published_at": "20251214T061500Z",
  "fetched_at": "2025-12-15T00:24:42.304457+00:00",
  "category": "semiconductors_compute",
  "subcategory": null,
  "keywords": [
    "ai"
  ],
  "location": "South Korea",
  "raw_data": {
    "url": "https://www.edaily.co.kr/News/Read?newsId=01646566642398520&mediaCodeNo=257",
    "url_mobile": "https://m.edaily.co.kr/News/Read?newsId=01646566642398520 eNo=257",
    "title": "\ube45\ud14c\ud06c AI\uce69 \ud328\uad8c \uc804\uc7c1 \u2026 \uc0bc\uc131 \u00b7 SK\ub3c4  \uba54\ubaa8\ub9ac \uc591\uac15  \uad73\ud78c\ub2e4",
    "seendate": "20251214T061500Z",
    "socialimage": "https://image.edaily.co.kr/images/Photo/files/NP/S/2025/12/PS25121400236.jpg",
    "domain": "edaily.co.kr",
    "language": "Korean",
    "sourcecountry": "South Korea"
  }
}