{
  "id": "3d3c8bdfa9740990",
  "title": "\u041d\u0430 \u0437\u0430\u043f\u0430\u0434\u043d\u043e\u043c \u0444\u0440\u043e\u043d\u0442\u0435 \u0435\u0441\u0442\u044c \u043f\u0435\u0440\u0435\u043c\u0435\u043d\u044b - \u0413\u0430\u0437\u0435\u0442\u0430 \u0422\u0440\u0443\u0434",
  "description": "20251224T223000Z",
  "content": "",
  "source": "trud.ru",
  "source_url": "https://www.trud.ru/article/25-12-2025/1770251_na_zapadnom_fronte_est_peremeny.html",
  "published_at": "20251224T223000Z",
  "fetched_at": "2025-12-25T00:22:49.565695+00:00",
  "category": "geopolitics_security",
  "subcategory": null,
  "keywords": [],
  "location": "Russia",
  "raw_data": {
    "url": "https://www.trud.ru/article/25-12-2025/1770251_na_zapadnom_fronte_est_peremeny.html",
    "url_mobile": "",
    "title": "\u041d\u0430 \u0437\u0430\u043f\u0430\u0434\u043d\u043e\u043c \u0444\u0440\u043e\u043d\u0442\u0435 \u0435\u0441\u0442\u044c \u043f\u0435\u0440\u0435\u043c\u0435\u043d\u044b - \u0413\u0430\u0437\u0435\u0442\u0430 \u0422\u0440\u0443\u0434",
    "seendate": "20251224T223000Z",
    "socialimage": "http://www.trud.ru/userfiles/gallery/f5/m_f5870eefbd9c853452d28fd7288d03d9.jpg",
    "domain": "trud.ru",
    "language": "Russian",
    "sourcecountry": "Russia"
  }
}