{
  "id": "7bd42d5e9f788029",
  "title": "SA On Track To Reach Key Climate Targets",
  "description": "20260105T004500Z",
  "content": "",
  "source": "miragenews.com",
  "source_url": "https://www.miragenews.com/sa-on-track-to-reach-key-climate-targets-1597212/",
  "published_at": "20260105T004500Z",
  "fetched_at": "2026-01-06T00:23:36.488656+00:00",
  "category": "climate_environment",
  "subcategory": null,
  "keywords": [
    "climate"
  ],
  "location": "United States",
  "raw_data": {
    "url": "https://www.miragenews.com/sa-on-track-to-reach-key-climate-targets-1597212/",
    "url_mobile": "",
    "title": "SA On Track To Reach Key Climate Targets",
    "seendate": "20260105T004500Z",
    "socialimage": "https://www.parliament.sa.gov.au/-/media/Project/Parliament/Images/Themes/EducationImage.jpg",
    "domain": "miragenews.com",
    "language": "English",
    "sourcecountry": "United States"
  }
}