{
  "id": "f7678d105e5cc713",
  "title": "Markets in 2025 : Gold , Goldilocks and the dollar bears | Hellenic Shipping News Worldwide",
  "description": "20260101T000000Z",
  "content": "",
  "source": "hellenicshippingnews.com",
  "source_url": "https://www.hellenicshippingnews.com/markets-in-2025-gold-goldilocks-and-the-dollar-bears-2/",
  "published_at": "20260101T000000Z",
  "fetched_at": "2026-01-01T00:26:23.010909+00:00",
  "category": "geopolitics_security",
  "subcategory": null,
  "keywords": [],
  "location": "China",
  "raw_data": {
    "url": "https://www.hellenicshippingnews.com/markets-in-2025-gold-goldilocks-and-the-dollar-bears-2/",
    "url_mobile": "",
    "title": "Markets in 2025 : Gold , Goldilocks and the dollar bears | Hellenic Shipping News Worldwide",
    "seendate": "20260101T000000Z",
    "socialimage": "",
    "domain": "hellenicshippingnews.com",
    "language": "English",
    "sourcecountry": "China"
  }
}