{
  "id": "a3a9af10675f50b6",
  "title": "Russisk censur udl\u00f8ser sj\u00e6lden demonstration",
  "description": "20251214T224500Z",
  "content": "",
  "source": "bt.dk",
  "source_url": "https://www.bt.dk/udland/russisk-censur-udloeser-sjaelden-demonstration",
  "published_at": "20251214T224500Z",
  "fetched_at": "2025-12-15T00:24:42.304457+00:00",
  "category": "politics_governance",
  "subcategory": null,
  "keywords": [],
  "location": "Denmark",
  "raw_data": {
    "url": "https://www.bt.dk/udland/russisk-censur-udloeser-sjaelden-demonstration",
    "url_mobile": "",
    "title": "Russisk censur udl\u00f8ser sj\u00e6lden demonstration",
    "seendate": "20251214T224500Z",
    "socialimage": "https://akamai-aptoma-production.bmcdn.dk/users/berlingske/images/140487355.webp?t[strip]=true&t[resize][width]=1440&t[quality]=70&accessToken=6bf0d161d85b83fb9de2ab75ff5bd9e29ea992ce751adea6e2c45318cdebb2e3",
    "domain": "bt.dk",
    "language": "Danish",
    "sourcecountry": "Denmark"
  }
}