{
  "id": "8ffdfd32f9d90125",
  "title": "Telix Pharmaceuticals in focus with China trial success and FDA updates",
  "description": "20251221T223000Z",
  "content": "",
  "source": "fool.com.au",
  "source_url": "https://www.fool.com.au/2025/12/22/telix-pharmaceuticals-in-focus-with-china-trial-success-and-fda-updates/",
  "published_at": "20251221T223000Z",
  "fetched_at": "2025-12-22T00:24:16.044990+00:00",
  "category": "health_biotech",
  "subcategory": null,
  "keywords": [
    "china",
    "fda"
  ],
  "location": "Australia",
  "raw_data": {
    "url": "https://www.fool.com.au/2025/12/22/telix-pharmaceuticals-in-focus-with-china-trial-success-and-fda-updates/",
    "url_mobile": "",
    "title": "Telix Pharmaceuticals in focus with China trial success and FDA updates",
    "seendate": "20251221T223000Z",
    "socialimage": "https://www.fool.com.au/wp-content/uploads/2024/08/clapping-16.9-1200x675.jpg",
    "domain": "fool.com.au",
    "language": "English",
    "sourcecountry": "Australia"
  }
}