{
  "id": "0614ba6b41ba0233",
  "title": "Streiks am Donnerstag : Lufthansa streicht 400 Starts und Landungen in Frankfurt",
  "description": "20260211T214500Z",
  "content": "",
  "source": "hessenschau.de",
  "source_url": "https://www.hessenschau.de/wirtschaft/streiks-am-donnerstag-lufthansa-streicht-400-starts-und-landungen-in-frankfurt-v7,lufthansa-streik-donnerstag-100.html",
  "published_at": "20260211T214500Z",
  "fetched_at": "2026-02-12T00:28:38.246764+00:00",
  "category": "labor_employment",
  "subcategory": null,
  "keywords": [],
  "location": "Germany",
  "raw_data": {
    "url": "https://www.hessenschau.de/wirtschaft/streiks-am-donnerstag-lufthansa-streicht-400-starts-und-landungen-in-frankfurt-v7,lufthansa-streik-donnerstag-100.html",
    "url_mobile": "",
    "title": "Streiks am Donnerstag : Lufthansa streicht 400 Starts und Landungen in Frankfurt",
    "seendate": "20260211T214500Z",
    "socialimage": "https://www.hessenschau.de/wirtschaft/tagesschau-image-153830~_t-1770835657761_v-16to9__retina.jpg",
    "domain": "hessenschau.de",
    "language": "German",
    "sourcecountry": "Germany"
  }
}