{
  "id": "8656b9ee3543685e",
  "title": "\ub7ec \u00b7 \uc6b0 \uc804\uc7c1 4\ub144 , \uc0ac\uc0c1\uc790 200\ub9cc \u00b7 \ud3c9\ud654\ub294  \uc2e0\uae30\ub8e8  [ \uae40\uacbd\ubbfc\uc758 \uc801\uc2dc\ud0c0 ] ",
  "description": "20260223T051500Z",
  "content": "",
  "source": "fnnews.com",
  "source_url": "https://www.fnnews.com/news/202602231222039943",
  "published_at": "20260223T051500Z",
  "fetched_at": "2026-02-24T00:28:11.413813+00:00",
  "category": "ai_machine_intelligence",
  "subcategory": null,
  "keywords": [],
  "location": "South Korea",
  "raw_data": {
    "url": "https://www.fnnews.com/news/202602231222039943",
    "url_mobile": "",
    "title": "\ub7ec \u00b7 \uc6b0 \uc804\uc7c1 4\ub144 , \uc0ac\uc0c1\uc790 200\ub9cc \u00b7 \ud3c9\ud654\ub294  \uc2e0\uae30\ub8e8  [ \uae40\uacbd\ubbfc\uc758 \uc801\uc2dc\ud0c0 ] ",
    "seendate": "20260223T051500Z",
    "socialimage": "https://image.fnnews.com/resource/media/image/2026/01/29/202601291559195603_l.jpg",
    "domain": "fnnews.com",
    "language": "Korean",
    "sourcecountry": "South Korea"
  }
}