{
  "id": "7dd5ca426bce3757",
  "title": "US to launch $12 - bn critical minerals stockpile to ease China reliance",
  "description": "20260203T054500Z",
  "content": "",
  "source": "spacewar.com",
  "source_url": "https://www.spacewar.com/reports/US_to_launch_12-bn_critical_minerals_stockpile_to_ease_China_reliance_999.html",
  "published_at": "20260203T054500Z",
  "fetched_at": "2026-02-04T00:26:40.270602+00:00",
  "category": "energy_resources",
  "subcategory": null,
  "keywords": [
    "china"
  ],
  "location": "Iraq",
  "raw_data": {
    "url": "https://www.spacewar.com/reports/US_to_launch_12-bn_critical_minerals_stockpile_to_ease_China_reliance_999.html",
    "url_mobile": "",
    "title": "US to launch $12 - bn critical minerals stockpile to ease China reliance",
    "seendate": "20260203T054500Z",
    "socialimage": "https://www.spxdaily.com/images-hg/pyykko-periodic-table-z172-hg.jpg",
    "domain": "spacewar.com",
    "language": "English",
    "sourcecountry": "Iraq"
  }
}