{
  "id": "f3fe42e82ae6db8e",
  "title": "Geopolitical risks keep Oil , Gas volatility elevated \u2013 Rabobank",
  "description": "20260120T180000Z",
  "content": "",
  "source": "fxstreet.com",
  "source_url": "https://www.fxstreet.com/news/geopolitical-risks-keep-oil-gas-volatility-elevated-rabobank-202601201554",
  "published_at": "20260120T180000Z",
  "fetched_at": "2026-01-21T00:24:36.527019+00:00",
  "category": "energy_resources",
  "subcategory": null,
  "keywords": [
    "bank",
    "oil"
  ],
  "location": "China",
  "raw_data": {
    "url": "https://www.fxstreet.com/news/geopolitical-risks-keep-oil-gas-volatility-elevated-rabobank-202601201554",
    "url_mobile": "https://www.fxstreet.com/amp/news/geopolitical-risks-keep-oil-gas-volatility-elevated-rabobank-202601201554",
    "title": "Geopolitical risks keep Oil , Gas volatility elevated \u2013 Rabobank",
    "seendate": "20260120T180000Z",
    "socialimage": "https://editorial.fxsstatic.com/images/i/Commodities_Gas-1_Medium.jpg",
    "domain": "fxstreet.com",
    "language": "English",
    "sourcecountry": "China"
  }
}