{
  "id": "32d10573ae63c46d",
  "title": "More diplomatic and economic tensions surface between China , Japan as a bumpy week ends",
  "description": "20260109T190000Z",
  "content": "",
  "source": "columbian.com",
  "source_url": "https://www.columbian.com/news/2026/jan/09/more-diplomatic-and-economic-tensions-surface-between-china-japan-as-a-bumpy-week-ends/",
  "published_at": "20260109T190000Z",
  "fetched_at": "2026-01-10T00:22:56.872596+00:00",
  "category": "geopolitics_security",
  "subcategory": null,
  "keywords": [
    "china"
  ],
  "location": "United States",
  "raw_data": {
    "url": "https://www.columbian.com/news/2026/jan/09/more-diplomatic-and-economic-tensions-surface-between-china-japan-as-a-bumpy-week-ends/",
    "url_mobile": "",
    "title": "More diplomatic and economic tensions surface between China , Japan as a bumpy week ends",
    "seendate": "20260109T190000Z",
    "socialimage": "https://www.columbian.com/wp-content/uploads/2026/01/China_Japan_At_Odds_Again_27787-c55a6.jpg",
    "domain": "columbian.com",
    "language": "English",
    "sourcecountry": "United States"
  }
}