{
  "id": "5a70e0e042d7adbe",
  "title": "Nigeria : lo que se sabe sobre los ataques a\u00e9reos de EE . UU . contra grupos yihadistas",
  "description": "20251227T213000Z",
  "content": "",
  "source": "rpp.pe",
  "source_url": "https://rpp.pe/mundo/actualidad/nigeria-lo-que-se-sabe-sobre-los-ataques-aereos-de-eeuu-contra-grupos-yihadistas-noticia-1669436",
  "published_at": "20251227T213000Z",
  "fetched_at": "2025-12-28T00:26:15.088259+00:00",
  "category": "politics_governance",
  "subcategory": null,
  "keywords": [],
  "location": "Peru",
  "raw_data": {
    "url": "https://rpp.pe/mundo/actualidad/nigeria-lo-que-se-sabe-sobre-los-ataques-aereos-de-eeuu-contra-grupos-yihadistas-noticia-1669436",
    "url_mobile": "",
    "title": "Nigeria : lo que se sabe sobre los ataques a\u00e9reos de EE . UU . contra grupos yihadistas",
    "seendate": "20251227T213000Z",
    "socialimage": "https://f.rpp-noticias.io/2025/12/27/165016_1824461.jpg?&quality=80",
    "domain": "rpp.pe",
    "language": "Spanish",
    "sourcecountry": "Peru"
  }
}