{
  "id": "60d3f01afb67b95d",
  "title": "Morning Notes for February 17 , 2026",
  "description": "20260217T150000Z",
  "content": "",
  "source": "arlnow.com",
  "source_url": "https://www.arlnow.com/2026/02/17/morning-notes-for-february-17-2026/",
  "published_at": "20260217T150000Z",
  "fetched_at": "2026-02-18T00:30:07.542614+00:00",
  "category": "labor_employment",
  "subcategory": null,
  "keywords": [],
  "location": "United States",
  "raw_data": {
    "url": "https://www.arlnow.com/2026/02/17/morning-notes-for-february-17-2026/",
    "url_mobile": "",
    "title": "Morning Notes for February 17 , 2026",
    "seendate": "20260217T150000Z",
    "socialimage": "https://www.arlnow.com/wp-content/uploads/2026/02/55076288117_5818ed36b4_b.jpg",
    "domain": "arlnow.com",
    "language": "English",
    "sourcecountry": "United States"
  }
}