{
  "id": "0f723aaadaf405da",
  "title": "EEUU realiza ataque militar en Venezuela contra narcotr\u00e1fico",
  "description": "20251229T230000Z",
  "content": "",
  "source": "noticiassin.com",
  "source_url": "https://www.noticiassin.com/eeuu-realiza-ataque-militar-en-venezuela-contra-narcotrafico-2025035",
  "published_at": "20251229T230000Z",
  "fetched_at": "2025-12-30T00:22:59.073919+00:00",
  "category": "labor_employment",
  "subcategory": null,
  "keywords": [],
  "location": "United States",
  "raw_data": {
    "url": "https://www.noticiassin.com/eeuu-realiza-ataque-militar-en-venezuela-contra-narcotrafico-2025035",
    "url_mobile": "https://noticiassin.com/eeuu-realiza-ataque-militar-en-venezuela-contra-narcotrafico-2025035?amp=1",
    "title": "EEUU realiza ataque militar en Venezuela contra narcotr\u00e1fico",
    "seendate": "20251229T230000Z",
    "socialimage": "https://noticiassin.blob.core.windows.net/images/2025/12/26/plan-de-paz-trump-zelenski-c09dd78f-focus-0-0-1200-675.webp",
    "domain": "noticiassin.com",
    "language": "Spanish",
    "sourcecountry": "United States"
  }
}