{
  "id": "37fcc082ce4b2e5a",
  "title": "Prediction : This AI Stock Could Be the Best Performer of 2026",
  "description": "20251220T164500Z",
  "content": "",
  "source": "fool.com",
  "source_url": "https://www.fool.com/investing/2025/12/20/prediction-this-ai-stock-could-be-the-best-perform/?source=iedfolrf0000001",
  "published_at": "20251220T164500Z",
  "fetched_at": "2025-12-21T00:24:51.714754+00:00",
  "category": "semiconductors_compute",
  "subcategory": null,
  "keywords": [
    "ai"
  ],
  "location": "United States",
  "raw_data": {
    "url": "https://www.fool.com/investing/2025/12/20/prediction-this-ai-stock-could-be-the-best-perform/?source=iedfolrf0000001",
    "url_mobile": "",
    "title": "Prediction : This AI Stock Could Be the Best Performer of 2026",
    "seendate": "20251220T164500Z",
    "socialimage": "https://g.foolcdn.com/editorial/images/844607/person-looking-at-wall-street-suit-stocks-finance.jpg",
    "domain": "fool.com",
    "language": "English",
    "sourcecountry": "United States"
  }
}