{
  "id": "c9843db6d87e1f8d",
  "title": "South Africa : Kruger National Park Rainfall Highlights Climate Change Challenges",
  "description": "20260116T110000Z",
  "content": "",
  "source": "allafrica.com",
  "source_url": "https://allafrica.com/stories/202601160188.html",
  "published_at": "20260116T110000Z",
  "fetched_at": "2026-01-17T00:22:29.333379+00:00",
  "category": "climate_environment",
  "subcategory": null,
  "keywords": [
    "climate",
    "ai"
  ],
  "location": "Nigeria",
  "raw_data": {
    "url": "https://allafrica.com/stories/202601160188.html",
    "url_mobile": "",
    "title": "South Africa : Kruger National Park Rainfall Highlights Climate Change Challenges",
    "seendate": "20260116T110000Z",
    "socialimage": "",
    "domain": "allafrica.com",
    "language": "English",
    "sourcecountry": "Nigeria"
  }
}