{
  "id": "f762005d28e97717",
  "title": "Streeting still ready to challenge Starmer despite show of unity , allies say",
  "description": "20260210T211500Z",
  "content": "",
  "source": "aol.co.uk",
  "source_url": "https://www.aol.co.uk/articles/streeting-still-ready-challenge-starmer-204629273.html",
  "published_at": "20260210T211500Z",
  "fetched_at": "2026-02-11T00:34:18.892628+00:00",
  "category": "politics_governance",
  "subcategory": null,
  "keywords": [],
  "location": "United Kingdom",
  "raw_data": {
    "url": "https://www.aol.co.uk/articles/streeting-still-ready-challenge-starmer-204629273.html",
    "url_mobile": "",
    "title": "Streeting still ready to challenge Starmer despite show of unity , allies say",
    "seendate": "20260210T211500Z",
    "socialimage": "https://s.yimg.com/cv/apiv2/aolfp/images/og-image.png",
    "domain": "aol.co.uk",
    "language": "English",
    "sourcecountry": "United Kingdom"
  }
}