{
  "id": "6bd38859a6c46350",
  "title": "ELTA glaustai : nuteistas parlamentaras Bagdono ir pa\u0161autas Rusijos generolas",
  "description": "20260206T173000Z",
  "content": "",
  "source": "delfi.lt",
  "source_url": "https://www.delfi.lt/naujienos/lietuvoje/elta-glaustai-nuteistas-parlamentaras-bagdono-ir-pasautas-rusijos-generolas-120208826",
  "published_at": "20260206T173000Z",
  "fetched_at": "2026-02-07T00:27:41.919994+00:00",
  "category": "geopolitics_security",
  "subcategory": null,
  "keywords": [
    "ai"
  ],
  "location": "Lithuania",
  "raw_data": {
    "url": "https://www.delfi.lt/naujienos/lietuvoje/elta-glaustai-nuteistas-parlamentaras-bagdono-ir-pasautas-rusijos-generolas-120208826",
    "url_mobile": "",
    "title": "ELTA glaustai : nuteistas parlamentaras Bagdono ir pa\u0161autas Rusijos generolas",
    "seendate": "20260206T173000Z",
    "socialimage": "https://images.delfi.lt/media-api-image-cropper/v1/6dfe922b-b00d-4d04-85ec-7edfba587490.jpg",
    "domain": "delfi.lt",
    "language": "Lithuanian",
    "sourcecountry": "Lithuania"
  }
}