{
  "id": "2d5c818758eb131d",
  "title": "Pr\u00f3bowa\u0142 rozwi\u0105za\u0107 zagadk\u0119 tw\u00f3rcy bitcoina .  Ju\u017c widzia\u0142em si\u0119 w roli zwyci\u0119zcy  ",
  "description": "20260101T124500Z",
  "content": "",
  "source": "newsweek.pl",
  "source_url": "https://www.newsweek.pl/biznes/probowal-rozwiazac-zagadke-tworcy-bitcoina-juz-widzialem-sie-w-roli-zwyciezcy/3835m0t",
  "published_at": "20260101T124500Z",
  "fetched_at": "2026-01-02T00:23:25.342374+00:00",
  "category": "ai_machine_intelligence",
  "subcategory": null,
  "keywords": [],
  "location": "Poland",
  "raw_data": {
    "url": "https://www.newsweek.pl/biznes/probowal-rozwiazac-zagadke-tworcy-bitcoina-juz-widzialem-sie-w-roli-zwyciezcy/3835m0t",
    "url_mobile": "",
    "title": "Pr\u00f3bowa\u0142 rozwi\u0105za\u0107 zagadk\u0119 tw\u00f3rcy bitcoina .  Ju\u017c widzia\u0142em si\u0119 w roli zwyci\u0119zcy  ",
    "seendate": "20260101T124500Z",
    "socialimage": "https://ocdn.eu/pulscms-transforms/1/FP0ktkpTURBXy9jY2JiY2M0MWE5MTcyYTM1MjkxNTgxMjY5MTMxMjUzMS5qcGeSlQMAzMPNB9DNBGWTBc0EsM0Cdg",
    "domain": "newsweek.pl",
    "language": "Polish",
    "sourcecountry": "Poland"
  }
}