{
  "id": "2dcccf3c8006cd6a",
  "title": "Plastic now outweighs all animals on Earth combined : Why this should alarm us",
  "description": "20260207T023000Z",
  "content": "",
  "source": "kashmirreader.com",
  "source_url": "https://kashmirreader.com/2026/02/07/plastic-now-outweighs-all-animals-on-earth-combined-why-this-should-alarm-us/",
  "published_at": "20260207T023000Z",
  "fetched_at": "2026-02-08T00:36:26.400151+00:00",
  "category": "climate_environment",
  "subcategory": null,
  "keywords": [],
  "location": "India",
  "raw_data": {
    "url": "https://kashmirreader.com/2026/02/07/plastic-now-outweighs-all-animals-on-earth-combined-why-this-should-alarm-us/",
    "url_mobile": "",
    "title": "Plastic now outweighs all animals on Earth combined : Why this should alarm us",
    "seendate": "20260207T023000Z",
    "socialimage": "",
    "domain": "kashmirreader.com",
    "language": "English",
    "sourcecountry": "India"
  }
}