{
  "id": "dae4f55daaea8421",
  "title": "Amazon Expects to Increase Spending on Amazon Leo by $1B in 2026",
  "description": "20260210T004500Z",
  "content": "",
  "source": "satellitetoday.com",
  "source_url": "https://www.satellitetoday.com/finance/2026/02/09/amazon-expects-to-increase-spending-on-amazon-leo-by-1b-in-2026/",
  "published_at": "20260210T004500Z",
  "fetched_at": "2026-02-11T00:34:18.892628+00:00",
  "category": "space_frontier",
  "subcategory": null,
  "keywords": [],
  "location": "United States",
  "raw_data": {
    "url": "https://www.satellitetoday.com/finance/2026/02/09/amazon-expects-to-increase-spending-on-amazon-leo-by-1b-in-2026/",
    "url_mobile": "",
    "title": "Amazon Expects to Increase Spending on Amazon Leo by $1B in 2026",
    "seendate": "20260210T004500Z",
    "socialimage": "",
    "domain": "satellitetoday.com",
    "language": "English",
    "sourcecountry": "United States"
  }
}