{
  "id": "19c0ce7181049bf7",
  "title": "Skeptical Science New Research for Week # 51 2025",
  "description": "20251218T101500Z",
  "content": "",
  "source": "skepticalscience.com",
  "source_url": "https://skepticalscience.com/new_research_2025_51.html",
  "published_at": "20251218T101500Z",
  "fetched_at": "2025-12-19T00:23:08.544189+00:00",
  "category": "climate_environment",
  "subcategory": null,
  "keywords": [],
  "location": "United States",
  "raw_data": {
    "url": "https://skepticalscience.com/new_research_2025_51.html",
    "url_mobile": "",
    "title": "Skeptical Science New Research for Week # 51 2025",
    "seendate": "20251218T101500Z",
    "socialimage": "https://skepticalscience.com/public/assets/images/og/button_sks2_200.jpg",
    "domain": "skepticalscience.com",
    "language": "English",
    "sourcecountry": "United States"
  }
}