{
  "id": "d95d5701dd0b5a38",
  "title": "Rezervo dar yra : darbo rink\u0105 gal\u0117t\u0173 papildyti negali\u0105 turintys asmenys",
  "description": "20260214T170000Z",
  "content": "",
  "source": "m.kauno.diena.lt",
  "source_url": "https://m.kauno.diena.lt/naujienos/verslas/ekonomika/rezervo-dar-yra-darbo-rinka-galetu-papildyti-negalia-turintys-asmenys-1741636",
  "published_at": "20260214T170000Z",
  "fetched_at": "2026-02-15T00:30:56.287245+00:00",
  "category": "ai_machine_intelligence",
  "subcategory": null,
  "keywords": [],
  "location": "Lithuania",
  "raw_data": {
    "url": "https://m.kauno.diena.lt/naujienos/verslas/ekonomika/rezervo-dar-yra-darbo-rinka-galetu-papildyti-negalia-turintys-asmenys-1741636",
    "url_mobile": "",
    "title": "Rezervo dar yra : darbo rink\u0105 gal\u0117t\u0173 papildyti negali\u0105 turintys asmenys",
    "seendate": "20260214T170000Z",
    "socialimage": "https://administravimas.diena.lt/sites/default/files-sync/2026-02/nn71h%2006.jpg",
    "domain": "m.kauno.diena.lt",
    "language": "Lithuanian",
    "sourcecountry": "Lithuania"
  }
}