{
  "id": "841b37257f2c4fa6",
  "title": "F\u00fchrungsf\u00e4higkeit sichern : Mobile Netzservicetrupps der Marine",
  "description": "20251218T113000Z",
  "content": "",
  "source": "bundeswehr.de",
  "source_url": "https://www.bundeswehr.de/de/organisation/marine/aktuelles/netzservicetrupp-it-ausruestung-marine-6053222",
  "published_at": "20251218T113000Z",
  "fetched_at": "2025-12-19T00:23:08.544189+00:00",
  "category": "robotics_automation",
  "subcategory": null,
  "keywords": [],
  "location": "Germany",
  "raw_data": {
    "url": "https://www.bundeswehr.de/de/organisation/marine/aktuelles/netzservicetrupp-it-ausruestung-marine-6053222",
    "url_mobile": "",
    "title": "F\u00fchrungsf\u00e4higkeit sichern : Mobile Netzservicetrupps der Marine",
    "seendate": "20251218T113000Z",
    "socialimage": "https://www.bundeswehr.de/resource/image/6053292/landscape_ratio16x9/3200/1800/9cfa698c14a2a63f21e8e7b4f4ef4f8/6CFF7BF7129E10A54C272E05B2192467/bodenansicht-hinten-links-offen.jpg",
    "domain": "bundeswehr.de",
    "language": "German",
    "sourcecountry": "Germany"
  }
}